CHANGELOG.rst
LICENSE
MANIFEST.in
README.rst
setup.cfg
setup.py
meta/__init__.py
meta/models.py
meta/settings.py
meta/views.py
meta/templates/meta.html
meta/templatetags/__init__.py
meta/templatetags/meta.py
ud_django_meta.egg-info/PKG-INFO
ud_django_meta.egg-info/SOURCES.txt
ud_django_meta.egg-info/dependency_links.txt
ud_django_meta.egg-info/requires.txt
ud_django_meta.egg-info/top_level.txt