Metadata-Version: 1.1
Name: ud-django-meta
Version: 0.2.1.dev1
Summary: Pluggable app for handling webpage meta tags and OpenGraph properties
Home-page: https://github.com/udemy/django-meta
Author: Udemy Developers
Author-email: dev@udemy.com
License: BSD
Platform: UNKNOWN
Classifier: Development Status :: 5 - Production/Stable
Classifier: Framework :: Django
Classifier: Environment :: Web Environment
Classifier: Intended Audience :: Developers
Classifier: License :: OSI Approved :: BSD License
Classifier: Programming Language :: Python :: 2.6
Classifier: Programming Language :: Python :: 2.7
Classifier: Programming Language :: Python :: 3.3
Classifier: Programming Language :: Python :: 3.4
